s3manager/__init__.py
s3manager-1.4.dist-info/LICENSE
s3manager-1.4.dist-info/METADATA
s3manager-1.4.dist-info/WHEEL
s3manager-1.4.dist-info/top_level.txt
s3manager-1.4.dist-info/RECORD
