Metadata-Version: 2.1
Name: s3manager
Version: 1.4
Summary: This packages helps to upload, download zip of multiple files, delete file from s3.
Home-page: https://github.com/anshul217/AWS-S3-MANAGER/
Author: Anshul Gupta
Author-email: anshulgupta217@gmail.com
License: UNKNOWN
Platform: UNKNOWN
Classifier: Programming Language :: Python :: 3
Classifier: License :: OSI Approved :: MIT License
Classifier: Operating System :: OS Independent
